spectrum_client/__init__.py
spectrum_client/__version__.py
spectrum_client/spectrum.py
spectrum_client-0.4.1.dist-info/LICENSE
spectrum_client-0.4.1.dist-info/METADATA
spectrum_client-0.4.1.dist-info/WHEEL
spectrum_client-0.4.1.dist-info/top_level.txt
spectrum_client-0.4.1.dist-info/RECORD
