Metadata-Version: 2.1
Name: spectrum-client
Version: 0.4.1
Summary: CA Spectrum Web Services API wrapper.
Home-page: https://github.com/orgito/spectrum-client
Author: Renato Orgito
Author-email: orgito@gmail.com
License: MIT
Project-URL: Bug Reports, https://github.com/orgito/spectrum-client/issues
Project-URL: Source, https://github.com/orgito/spectrum-client
Keywords: spectrum-client network monitoring spectrum
Classifier: Development Status :: 4 - Beta
Classifier: Intended Audience :: Developers
Classifier: Intended Audience :: Information Technology
Classifier: Intended Audience :: System Administrators
Classifier: License :: OSI Approved :: MIT License
Classifier: Natural Language :: English
Classifier: Operating System :: OS Independent
Classifier: Programming Language :: Python :: 3.4
Classifier: Programming Language :: Python :: 3.5
Classifier: Programming Language :: Python :: 3.6
Classifier: Programming Language :: Python :: 3.7
Classifier: Programming Language :: Python :: 3.8
Classifier: Programming Language :: Python :: 3.9
Classifier: Programming Language :: Python :: 3.10
Classifier: Topic :: Software Development :: Libraries
Classifier: Topic :: System :: Monitoring
Classifier: Topic :: System :: Networking :: Monitoring
Requires-Python: >=3.4
License-File: LICENSE
Requires-Dist: requests
